gcs_lock_thing/__init__.py
gcs_lock_thing/lock.py
gcs_lock_thing-0.0.6.dist-info/LICENSE
gcs_lock_thing-0.0.6.dist-info/METADATA
gcs_lock_thing-0.0.6.dist-info/WHEEL
gcs_lock_thing-0.0.6.dist-info/dependency_links.txt
gcs_lock_thing-0.0.6.dist-info/top_level.txt
gcs_lock_thing-0.0.6.dist-info/RECORD
