Metadata-Version: 2.1
Name: gcs-lock-thing
Version: 0.0.6
Summary: Python Boilerplate contains all the boilerplate you need to create a Python package.
Home-page: https://github.com/connor-ps/gcs_lock_thing
Author: connor mcshane
Author-email: connor.mcshane@paymentsense.com
License: MIT license
Keywords: gcs_lock_thing
Platform: UNKNOWN
Classifier: Development Status :: 2 - Pre-Alpha
Classifier: Intended Audience :: Developers
Classifier: License :: OSI Approved :: MIT License
Classifier: Natural Language :: English
Classifier: Programming Language :: Python :: 3
Classifier: Programming Language :: Python :: 3.7
Classifier: Programming Language :: Python :: 3.8
Classifier: Programming Language :: Python :: 3.9
Requires-Python: >=3.7
License-File: LICENSE
Requires-Dist: backoff (==1.11.1)
Requires-Dist: google-cloud-storage (==1.31.0)
Requires-Dist: pytz
